{
    "Name": "Honkai: Star Rail",
    "Description": "Unedited playthrough",
    "List": [
        {
            "Name": "Silver Chariot, Away to that Blackened Land Part 1",
            "Name_Alt": "Heroic Saga of Flame Chase",
            "Description": "",
            "Thumbnail": "https://i9.ytimg.com/vi/ZMFJNDRJ3PQ/mqdefault.jpg?sqp=CPClycMG-oaymwEmCMACELQB8quKqQMa8AEB-AH-CYAC0AWKAgwIABABGC0gWCh_MA8=&rs=AOn4CLDZGgCyFLOZYGwqsv8RIG_YlViplA",
            "Video": "https://youtu.be/ZMFJNDRJ3PQ",
            "ViewableInSite": true
        },
        {
            "Name": "Silver Chariot, Away to that Blackened Land Part 2",
            "Name_Alt": "Heroic Saga of Flame Chase",
            "Description": "",
            "Thumbnail": "https://i9.ytimg.com/vi/Xc-YCYEUfb0/mqdefault.jpg?sqp=CPClycMG-oaymwEmCMACELQB8quKqQMa8AEB-AH-CYAC0AWKAgwIABABGDAgJyh_MA8=&rs=AOn4CLBExho6kOvEqn1gcqJ4bo9-j-6xGA",
            "Video": "https://youtu.be/Xc-YCYEUfb0",
            "ViewableInSite": true
        },
        {
            "Name": "Night Stars, Accompany my Slumber & Wasteland, Hark Back Glory of Old",
            "Name_Alt": "Heroic Saga of Flame Chase",
            "Description": "",
            "Thumbnail": "https://i9.ytimg.com/vi/cRGxOzZ0CqQ/mqdefault.jpg?sqp=CPClycMG-oaymwEmCMACELQB8quKqQMa8AEB-AH-CYAC0AWKAgwIABABGEMgZSguMA8=&rs=AOn4CLCj3tLO7pZFhA584AX00NWLfHUcIQ",
            "Video": "https://youtu.be/cRGxOzZ0CqQ",
            "ViewableInSite": true
        },
        {
            "Name": "Night Veil, Shroud the Silent Past",
            "Name_Alt": "Heroic Saga of Flame Chase",
            "Description": "",
            "Thumbnail": "https://i9.ytimg.com/vi/AI_c98eoDrU/mqdefault.jpg?sqp=CJyoycMG-oaymwEmCMACELQB8quKqQMa8AEB-AH-CYAC0AWKAgwIABABGDMgVCh_MA8=&rs=AOn4CLDYNXFgwJywk4hzUBEVMprgnHTDIA",
            "Video": "https://youtu.be/AI_c98eoDrU",
            "ViewableInSite": true
        },
        {
            "Name": "Kremnos, Cleanse Thy Rusted Blood I",
            "Name_Alt": "Heroic Saga of Flame Chase",
            "Description": "",
            "Thumbnail": "https://i9.ytimg.com/vi/GR1er-vYGzI/mqdefault.jpg?sqp=CJyoycMG-oaymwEmCMACELQB8quKqQMa8AEB-AH-CYAC0AWKAgwIABABGEMgWChlMA8=&rs=AOn4CLBnXjyrzMcOSoCczY8PcKJecHI4nQ",
            "Video": "https://youtu.be/GR1er-vYGzI",
            "ViewableInSite": true
        },
        {
            "Name": "A Cleansing of Gold",
            "Name_Alt": "Heroic Saga of Flame Chase",
            "Description": "",
            "Thumbnail": "https://i9.ytimg.com/vi/dP1j8jcoqe4/mqdefault.jpg?sqp=CJyoycMG-oaymwEmCMACELQB8quKqQMa8AEB-AH-CYAC0AWKAgwIABABGEQgTChyMA8=&rs=AOn4CLCPNMF-_CoJ12L2KIGnNdXi8MHtkA",
            "Video": "https://youtu.be/dP1j8jcoqe4",
            "ViewableInSite": true
        },
        {
            "Name": "Kremnos, Cleanse Thy Rusted Blood II",
            "Name_Alt": "Heroic Saga of Flame Chase",
            "Description": "",
            "Thumbnail": "https://i9.ytimg.com/vi/gZ5fnL3B08U/mqdefault.jpg?sqp=CJyoycMG-oaymwEmCMACELQB8quKqQMa8AEB-AH-CYAC0AWKAgwIABABGGUgWihNMA8=&rs=AOn4CLDGSB-Y9xfM8vlR0NA6jf_-5L0ODg",
            "Video": "https://youtu.be/gZ5fnL3B08U",
            "ViewableInSite": true
        },
        {
            "Name": "A Witch's Scientific Repose",
            "Name_Alt": "Heroic Saga of Flame Chase",
            "Description": "",
            "Thumbnail": "https://i9.ytimg.com/vi/RqSl_3UHN_Y/mqdefault.jpg?sqp=CPClycMG-oaymwEmCMACELQB8quKqQMa8AEB-AH-CYAC0AWKAgwIABABGHIgNShOMA8=&rs=AOn4CLAY51ees5b_C0LfDbXsJU53A6HJ0w",
            "Video": "https://youtu.be/RqSl_3UHN_Y",
            "ViewableInSite": true
        },
        {
            "Name": "Hero, Bear Thy Coreflame",
            "Name_Alt": "Heroic Saga of Flame Chase",
            "Description": "",
            "Thumbnail": "https://i9.ytimg.com/vi/UviqUMF-Vbc/mqdefault.jpg?sqp=CPClycMG-oaymwEmCMACELQB8quKqQMa8AEB-AH-CYAC0AWKAgwIABABGBYgNih_MA8=&rs=AOn4CLClMrJmxC6CUcsyKlavYwDaBddaqg",
            "Video": "https://youtu.be/UviqUMF-Vbc",
            "ViewableInSite": true
        },
        {
            "Name": "Saber & Archer Trial Level",
            "Name_Alt": "Fate Collab",
            "Description": "",
            "Thumbnail": "https://i9.ytimg.com/vi/32dsgFU261g/mqdefault.jpg?sqp=CJyoycMG-oaymwEmCMACELQB8quKqQMa8AEB-AH-CYAC0AWKAgwIABABGH8gEygiMA8=&rs=AOn4CLAL69_p6EwB8C5Ng6AANQH1K--20A",
            "Video": "https://youtu.be/32dsgFU261g",
            "ViewableInSite": true
        },
        {
            "Name": "Strife, Dispel the Accompanying Fears",
            "Name_Alt": "Light Slips the Gate, Shadow Greets the Throne",
            "Description": "",
            "Thumbnail": "https://i.ytimg.com/vi/N-QfLsX27Rc/hqdefault.jpg?sqp=-oaymwFBCPYBEIoBSFryq4qpAzMIARUAAIhCGAHYAQHiAQoIGBACGAY4AUAB8AEB-AH-CYAC0AWKAgwIABABGGUgRShGMA8=&rs=AOn4CLDfuwXJNUfD9ofGfwLJt2I3nm4o7Q",
            "Video": "https://youtu.be/N-QfLsX27Rc",
            "ViewableInSite": true
        },
        {
            "Name": "Glory, Turn from Imbibed Prison",
            "Name_Alt": "Light Slips the Gate, Shadow Greets the Throne",
            "Description": "",
            "Thumbnail": "https://i9.ytimg.com/vi/3hP9k3eFoAk/mqdefault.jpg?sqp=CODO5MMG-oaymwEmCMACELQB8quKqQMa8AEB-AH-CYAC0AWKAgwIABABGEMgXShyMA8=&rs=AOn4CLCyu5Isa1BCDRRgVU_ngth7kTBYog",
            "Video": "https://youtu.be/3hP9k3eFoAk",
            "ViewableInSite": true
        },
        {
            "Name": "Grove, Wherefore are the Wise Silent",
            "Name_Alt": "Light Slips the Gate, Shadow Greets the Throne",
            "Description": "",
            "Thumbnail": "https://i9.ytimg.com/vi/24e8dXOb8gg/mqdefault.jpg?sqp=CODO5MMG-oaymwEmCMACELQB8quKqQMa8AEB-AH-CYAC0AWKAgwIABABGEogWyhlMA8=&rs=AOn4CLCu40-NtYaFmNxKAvampl-6nzkq4Q",
            "Video": "https://youtu.be/24e8dXOb8gg",
            "ViewableInSite": true
        },
        {
            "Name": "Lamentations, Bring Not Empty Tears",
            "Name_Alt": "Light Slips the Gate, Shadow Greets the Throne",
            "Description": "",
            "Thumbnail": "https://i9.ytimg.com/vi/7dj4MKriApM/mqdefault.jpg?v=6875f6b5&sqp=CODO5MMG&rs=AOn4CLCNDscMPgdO1xGVXT_k-aaVod0FyQ",
            "Video": "https://youtu.be/7dj4MKriApM",
            "ViewableInSite": true
        },
        {
            "Name": "Memories, Veiled in Blazing Mist",
            "Name_Alt": "Light Slips the Gate, Shadow Greets the Throne",
            "Description": "",
            "Thumbnail": "https://i9.ytimg.com/vi/uQVODBLY4JI/mqdefault.jpg?v=6875f754&sqp=CODO5MMG&rs=AOn4CLDjwIXWtbtXefZl-7skg_tDWYKW7A",
            "Video": "https://youtu.be/uQVODBLY4JI",
            "ViewableInSite": true
        },
        {
            "Name": "Passages, Knocking Echoes in Dreams",
            "Name_Alt": "Light Slips the Gate, Shadow Greets the Throne",
            "Description": "",
            "Thumbnail": "https://i9.ytimg.com/vi/9o0LZz9c_wI/mqdefault.jpg?v=6875f7c4&sqp=CODO5MMG&rs=AOn4CLCskJJchtVnzIqN6g2OBzM0RTyMKw",
            "Video": "https://youtu.be/9o0LZz9c_wI",
            "ViewableInSite": true
        },
        {
            "Name": "Nemesis, Scorched by Golden Blood",
            "Name_Alt": "Light Slips the Gate, Shadow Greets the Throne",
            "Description": "",
            "Thumbnail": "https://i9.ytimg.com/vi/t-M_LhTFaMo/mqdefault.jpg?v=6875f888&sqp=CODO5MMG&rs=AOn4CLCsB7WjxCasQuv7ZKFuGywZ2rYa4A",
            "Video": "https://youtu.be/t-M_LhTFaMo",
            "ViewableInSite": true
        },
        {
            "Name": "Throne, End Those Long Years Forlorn",
            "Name_Alt": "Light Slips the Gate, Shadow Greets the Throne",
            "Description": "",
            "Thumbnail": "https://i9.ytimg.com/vi/dM0UH2PoVDc/mqdefault.jpg?v=6876952f&sqp=CODO5MMG&rs=AOn4CLCYzURijB8Q76DPHREASU5sQRPsrg",
            "Video": "https://youtu.be/dM0UH2PoVDc",
            "ViewableInSite": true
        },
        {
            "Name": "Passage, Reveal the Past Once More",
            "Name_Alt": "Light Slips the Gate, Shadow Greets the Throne",
            "Description": "",
            "Thumbnail": "https://i9.ytimg.com/vi/N24ycSeg8ho/mqdefault.jpg?v=6876959f&sqp=CODO5MMG&rs=AOn4CLCrc4SuWXBtSqrItAHqADp6d6SYwQ",
            "Video": "https://youtu.be/N24ycSeg8ho",
            "ViewableInSite": true
        },
        {
            "Name": "Spindle, Laboring to Weabe the Tapestry of Time",
            "Name_Alt": "Through the Petals in the Land of Repose",
            "Description": "",
            "Thumbnail": "https://i9.ytimg.com/vi/AkK5vHVN3E8/mqdefault.jpg?v=6877d8b7&sqp=CODO5MMG&rs=AOn4CLBBSVA3mZyx9BmiWqGitu10ECXZ-w",
            "Video": "https://youtu.be/AkK5vHVN3E8",
            "ViewableInSite": true
        }
    ]
}
